trellozilla/__init__.py
trellozilla/__main__.py
trellozilla/core/__init__.py
trellozilla/core/bugzilla.py
trellozilla/core/config.py
trellozilla/core/trello.py
trellozilla/jobs/__init__.py
trellozilla/jobs/generate_trello_oauth_token.py
trellozilla-0.2.0.dist-info/AUTHORS
trellozilla-0.2.0.dist-info/LICENSE
trellozilla-0.2.0.dist-info/METADATA
trellozilla-0.2.0.dist-info/WHEEL
trellozilla-0.2.0.dist-info/entry_points.txt
trellozilla-0.2.0.dist-info/pbr.json
trellozilla-0.2.0.dist-info/top_level.txt
trellozilla-0.2.0.dist-info/RECORD
