Metadata-Version: 2.1
Name: trellozilla
Version: 0.2.0
Summary: TrelloZilla is a small set of boilerplate code to speed up automations in/between both Bugzilla and Trello.
Home-page: https://github.com/moisesguimaraes/trellozilla/
Author: Moisés Guimarães de Medeiros
Author-email: moguimar@redhat.com
License: Apache-2.0
Platform: UNKNOWN
Classifier: Development Status :: 4 - Beta
Classifier: Intended Audience :: Developers
Classifier: License :: OSI Approved :: Apache Software License
Classifier: Natural Language :: English
Classifier: Programming Language :: Python
Classifier: Programming Language :: Python :: 3
Classifier: Programming Language :: Python :: 3.6
Classifier: Programming Language :: Python :: 3.7
Classifier: Programming Language :: Python :: 3.8
Classifier: Programming Language :: Python :: 3.9
Classifier: Environment :: OpenStack
Requires-Dist: pbr (!=2.1.0,>=2.0.0)
Requires-Dist: oslo.config (>=6.11.0)
Requires-Dist: oslo.log (>=3.44.1)
Requires-Dist: python-bugzilla (>=2.2.0)
Requires-Dist: py-trello (>=0.15.0)
